<annotation>
	<folder>truck</folder>
	<filename>447 Indian Truck Driver Stock Videos... (1).jpg</filename>
	<path>E:\images\truck\447 Indian Truck Driver Stock Videos... (1).jpg</path>
	<source>
		<database>Unknown</database>
	</source>
	<size>
		<width>640</width>
		<height>360</height>
		<depth>3</depth>
	</size>
	<segmented>0</segmented>
	<object>
		<name>truck</name>
		<pose>Unspecified</pose>
		<truncated>0</truncated>
		<difficult>0</difficult>
		<bndbox>
			<xmin>289</xmin>
			<ymin>187</ymin>
			<xmax>330</xmax>
			<ymax>235</ymax>
		</bndbox>
	</object>
	<object>
		<name>left turn</name>
		<pose>Unspecified</pose>
		<truncated>0</truncated>
		<difficult>0</difficult>
		<bndbox>
			<xmin>541</xmin>
			<ymin>203</ymin>
			<xmax>575</xmax>
			<ymax>239</ymax>
		</bndbox>
	</object>
	<object>
		<name>left turn</name>
		<pose>Unspecified</pose>
		<truncated>0</truncated>
		<difficult>0</difficult>
		<bndbox>
			<xmin>484</xmin>
			<ymin>207</ymin>
			<xmax>503</xmax>
			<ymax>231</ymax>
		</bndbox>
	</object>
	<object>
		<name>left turn</name>
		<pose>Unspecified</pose>
		<truncated>0</truncated>
		<difficult>0</difficult>
		<bndbox>
			<xmin>450</xmin>
			<ymin>210</ymin>
			<xmax>466</xmax>
			<ymax>227</ymax>
		</bndbox>
	</object>
	<object>
		<name>left turn</name>
		<pose>Unspecified</pose>
		<truncated>0</truncated>
		<difficult>0</difficult>
		<bndbox>
			<xmin>434</xmin>
			<ymin>210</ymin>
			<xmax>444</xmax>
			<ymax>224</ymax>
		</bndbox>
	</object>
	<object>
		<name>left turn</name>
		<pose>Unspecified</pose>
		<truncated>0</truncated>
		<difficult>0</difficult>
		<bndbox>
			<xmin>423</xmin>
			<ymin>211</ymin>
			<xmax>432</xmax>
			<ymax>222</ymax>
		</bndbox>
	</object>
	<object>
		<name>left turn</name>
		<pose>Unspecified</pose>
		<truncated>0</truncated>
		<difficult>0</difficult>
		<bndbox>
			<xmin>414</xmin>
			<ymin>210</ymin>
			<xmax>421</xmax>
			<ymax>221</ymax>
		</bndbox>
	</object>
	<object>
		<name>left turn</name>
		<pose>Unspecified</pose>
		<truncated>0</truncated>
		<difficult>0</difficult>
		<bndbox>
			<xmin>409</xmin>
			<ymin>211</ymin>
			<xmax>415</xmax>
			<ymax>220</ymax>
		</bndbox>
	</object>
	<object>
		<name>left turn</name>
		<pose>Unspecified</pose>
		<truncated>0</truncated>
		<difficult>0</difficult>
		<bndbox>
			<xmin>404</xmin>
			<ymin>212</ymin>
			<xmax>409</xmax>
			<ymax>220</ymax>
		</bndbox>
	</object>
</annotation>
